AUTHORS
CHANGELOG.txt
DESCRIPTION
LICENSE
MANIFEST.in
setup.py
cmsplugin_filer_image_translated/__init__.py
cmsplugin_filer_image_translated/admin.py
cmsplugin_filer_image_translated/models.py
cmsplugin_filer_image_translated/views.py
cmsplugin_filer_image_translated.egg-info/PKG-INFO
cmsplugin_filer_image_translated.egg-info/SOURCES.txt
cmsplugin_filer_image_translated.egg-info/dependency_links.txt
cmsplugin_filer_image_translated.egg-info/requires.txt
cmsplugin_filer_image_translated.egg-info/top_level.txt
cmsplugin_filer_image_translated/fixtures/bootstrap_auth.json
cmsplugin_filer_image_translated/fixtures/bootstrap_cms.json
cmsplugin_filer_image_translated/fixtures/bootstrap_cms2.json
cmsplugin_filer_image_translated/fixtures/bootstrap_sites.json
cmsplugin_filer_image_translated/migrations/0001_initial.py
cmsplugin_filer_image_translated/migrations/0002_create_translation_for_all_images.py
cmsplugin_filer_image_translated/migrations/0003_temporarily_rename_translation_model.py
cmsplugin_filer_image_translated/migrations/0004_auto__add_imagetranslationtranslation__add_unique_imagetranslationtran.py
cmsplugin_filer_image_translated/migrations/0005_move_data_from_simpletrans_to_hvad.py
cmsplugin_filer_image_translated/migrations/0006_auto__del_imagetranslationrenamed.py
cmsplugin_filer_image_translated/migrations/__init__.py
cmsplugin_filer_image_translated/settings/__init__.py
cmsplugin_filer_image_translated/settings/app_settings.py
cmsplugin_filer_image_translated/settings/test_settings.py
cmsplugin_filer_image_translated/templates/admin/filer/image/change_form.html
cmsplugin_filer_image_translated/templates/cmsplugin_filer_image/image.html
cmsplugin_filer_image_translated/tests/__init__.py
cmsplugin_filer_image_translated/tests/factories.py
cmsplugin_filer_image_translated/tests/models_tests.py
cmsplugin_filer_image_translated/tests/test_app/__init__.py
cmsplugin_filer_image_translated/tests/test_app/urls.py
cmsplugin_filer_image_translated/tests/test_app/templates/400.html
cmsplugin_filer_image_translated/tests/test_app/templates/500.html
cmsplugin_filer_image_translated/tests/test_app/templates/base.html
cmsplugin_filer_image_translated/tests/test_app/templates/admin/filer/image/change_form.html
