Metadata-Version: 1.0
Name: cmsplugin-filer-image-translated
Version: 0.2
Summary: Adds simple-translation to the Image admin of cmsplugin-filer
